yamldown/__init__.py
yamldown/yamldown.py
yamldown-0.1.8.dist-info/LICENSE
yamldown-0.1.8.dist-info/METADATA
yamldown-0.1.8.dist-info/WHEEL
yamldown-0.1.8.dist-info/top_level.txt
yamldown-0.1.8.dist-info/RECORD
