Metadata-Version: 1.1
Name: yamldown
Version: 0.1.8
Summary: Python library for loading and dumping "yamldown" (markdown with embedded yaml) files.
Home-page: https://github.com/dougli1sqrd/yamldown
Author: edouglass
Author-email: edouglass@lbl.gov
License: UNKNOWN
Download-URL: https://github.com/dougli1sqrd/yamldown/archive/0.1.8.tar.gz
Keywords: yaml,markdown
Platform: UNKNOWN
